nbtools/__init__.py
nbtools/core.py
nbtools/exec_notebook.py
nbtools/pylint_notebook.py
nbtools/nbstat/__init__.py
nbtools/nbstat/cli.py
nbtools/nbstat/resource.py
nbtools/nbstat/resource_entry.py
nbtools/nbstat/resource_formatter.py
nbtools/nbstat/resource_inspector.py
nbtools/nbstat/resource_table.py
nbtools/nbstat/utils.py
py_nbtools-0.9.15.dist-info/licenses/LICENSE
py_nbtools-0.9.15.dist-info/METADATA
py_nbtools-0.9.15.dist-info/WHEEL
py_nbtools-0.9.15.dist-info/entry_points.txt
py_nbtools-0.9.15.dist-info/top_level.txt
py_nbtools-0.9.15.dist-info/RECORD
