Metadata-Version: 2.4
Name: py-nbtools
Version: 0.9.15
Summary: A collection of tools for using inside Jupyter Notebooks
Author-email: Sergey Tsimfer <sergeytsimfer@gmail.com>
License: Apache License 2.0
Project-URL: Homepage, https://github.com/analysiscenter/nbtools
Project-URL: Repository, https://github.com/analysiscenter/nbtools
Classifier: Development Status :: 4 - Beta
Classifier: Intended Audience :: Developers
Classifier: Intended Audience :: Science/Research
Classifier: License :: OSI Approved :: Apache Software License
Classifier: Operating System :: OS Independent
Classifier: Programming Language :: Python
Classifier: Programming Language :: Python :: 3.10
Classifier: Programming Language :: Python :: 3.11
Classifier: Programming Language :: Python :: 3.12
Classifier: Topic :: System :: Monitoring
Requires-Python: >=3.10
License-File: LICENSE
Requires-Dist: nvidia-ml-py>=12.0.0
Requires-Dist: blessed>=1.17
Requires-Dist: psutil>=5.6
Requires-Dist: requests>=2.24
Provides-Extra: nbrun
Requires-Dist: ipython>=7.10.0; extra == "nbrun"
Requires-Dist: nbconvert>=5.6.1; extra == "nbrun"
Provides-Extra: linter
Requires-Dist: pylint; extra == "linter"
Provides-Extra: dev
Requires-Dist: ruff>=0.1.0; extra == "dev"
Dynamic: license-file
